test_policy_package/__init__.py
test_policy_package/lfn2pfn.py
test_policy_package/non_deterministic_pfn.py
test_policy_package/permission.py
test_policy_package/pfn2lfn.py
test_policy_package/schema.py
test_policy_package/scope.py
test_policy_package/tape_metadata.py
test_policy_package-0.0.1.dist-info/licenses/LICENSE
test_policy_package-0.0.1.dist-info/METADATA
test_policy_package-0.0.1.dist-info/WHEEL
test_policy_package-0.0.1.dist-info/top_level.txt
test_policy_package-0.0.1.dist-info/RECORD
