Metadata-Version: 2.4
Name: test_policy_package
Version: 0.0.1
Summary: Rucio template policy package
Author-email: test_policy_package <placeholder@placeholder.com>
License:                                  Apache License
Classifier: Programming Language :: Python :: 3
Classifier: Operating System :: OS Independent
Requires-Python: >=3.9
License-File: LICENSE
Provides-Extra: dev
Requires-Dist: rucio>=35.5.0; extra == "dev"
Dynamic: license-file
